pyhan/__init__.py
pyhan/han.py
pyhan/files/st00.csv
pyhan/files/st02.csv
test/__init__.py
test/han.py
tool/__init__.py
tool/han.py
pyhan-0.0.22.dist-info/LICENSE
pyhan-0.0.22.dist-info/METADATA
pyhan-0.0.22.dist-info/WHEEL
pyhan-0.0.22.dist-info/top_level.txt
pyhan-0.0.22.dist-info/RECORD
