Metadata-Version: 2.2
Name: pyhan
Version: 0.0.22
Summary: 簡化字轉漢字
Home-page: https://github.com/lizongying/pyhan
Author: Li ZongYing
Author-email: lizongying@msn.com
Project-URL: Bug Tracker, https://github.com/lizongying/pyhan/issues
Classifier: Programming Language :: Python :: 3
Classifier: License :: OSI Approved :: MIT License
Classifier: Operating System :: OS Independent
Requires-Python: >=3.6
License-File: LICENSE
